<?xml version="1.0"?>
<msg>
	<appmsg appid="" sdkver="0">
		<title>手哥你看我这操作6不</title>
		<type>57</type>
		<appattach>
			<cdnthumbaeskey />
			<aeskey></aeskey>
		</appattach>
		<refermsg>
			<type>3</type>
			<svrid>4131907196268641300</svrid>
			<fromusr>wxid_yaymhyamx8kq22</fromusr>
			<chatusr />
			<displayname>W</displayname>
			<content>&lt;msg&gt;&lt;img hdlength="0" length="80734" aeskey="6ef65a538d3044619d16f6be96229cf3" encryver="1" md5="142faa947f3cb8a7fd194d6902db4efe" originsourcemd5="e7aed16d730f42c6f1b3251af72f2df8" filekey="wxid_osl6cosuread12_4212_1740561228" uploadcontinuecount="0" imgsourceurl="" hevc_mid_size="80734" cdnbigimgurl="" cdnmidimgurl="3057020100044b30490201000204e2d905f802032f565d02041041aa3d020467bec16a042465353630623336302d626135302d343165612d393530362d306566323435393132383766020405190a020201000405004c56f900" cdnthumburl="3057020100044b30490201000204e2d905f802032f565d02041041aa3d020467bec16a042465353630623336302d626135302d343165612d393530362d306566323435393132383766020405190a020201000405004c56f900" cdnthumblength="2786" cdnthumbwidth="55" cdnthumbheight="120" cdnthumbaeskey=""&gt;&lt;secHashInfoBase64&gt;eyJwaGFzaCI6IjEwMTAwMDAwMDAwMDAwMDAiLCJwZHFoYXNoIjoiNWU0NGIzYTM1NTQ2YmJiMzc1NDRhOGFiNzQ1NGIyYmI1ZGU0NGIzYmIwOGY0NTY0MGIyYjU2NGNhYWJiNDQ2YyJ9&lt;/secHashInfoBase64&gt;&lt;/img&gt;&lt;appinfo&gt;&lt;appid&gt;&lt;/appid&gt;&lt;appname&gt;&lt;/appname&gt;&lt;version&gt;0&lt;/version&gt;&lt;isforceupdate&gt;1&lt;/isforceupdate&gt;&lt;mediatagname&gt;&lt;/mediatagname&gt;&lt;messageext&gt;&lt;/messageext&gt;&lt;messageaction&gt;&lt;/messageaction&gt;&lt;/appinfo&gt;&lt;MMAsset&gt;&lt;m_assetUrlForSystem&gt;&lt;![CDATA[E5FA9720-825B-44F6-85E8-47FBA888637A/L0/001]]&gt;&lt;/m_assetUrlForSystem&gt;&lt;m_isNeedOriginImage&gt;0&lt;/m_isNeedOriginImage&gt;&lt;m_isFailedFromIcloud&gt;0&lt;/m_isFailedFromIcloud&gt;&lt;m_isLoadingFromIcloud&gt;0&lt;/m_isLoadingFromIcloud&gt;&lt;m_isUseLivePhoto&gt;0&lt;/m_isUseLivePhoto&gt;&lt;/MMAsset&gt;&lt;/msg&gt;</content>
			<msgsource>&lt;msgsource&gt;&lt;svr_create_time&gt;1740561229&lt;/svr_create_time&gt;&lt;bizflag&gt;0&lt;/bizflag&gt;&lt;sec_msg_node&gt;&lt;uuid&gt;&lt;![CDATA[da72ed48429951992d675f60f14e4c81_]]&gt;&lt;/uuid&gt;&lt;/sec_msg_node&gt;&lt;/msgsource&gt;</msgsource>
			<createtime>1740561229</createtime>
		</refermsg>
	</appmsg>
	<fromusername>wxid_yaymhyamx8kq22</fromusername>
	<scene>0</scene>
	<appinfo>
		<version>1</version>
		<appname />
	</appinfo>
	<commenturl />
</msg>
